fiachia/__init__.py
fiachia/log.py
fiachia/printf.py
fiachia_log-1.0.2.dist-info/licenses/licence.txt
fiachia_log-1.0.2.dist-info/METADATA
fiachia_log-1.0.2.dist-info/WHEEL
fiachia_log-1.0.2.dist-info/top_level.txt
fiachia_log-1.0.2.dist-info/RECORD
