Metadata-Version: 2.4
Name: fiachia-log
Version: 1.0.2
Summary: Easy print and log with color
Home-page: 
Author: fiachia
Author-email: 208473302@qq.com
Maintainer: fiachia
Maintainer-email: 208473302@qq.com
License: BSD License
Platform: all
License-File: licence.txt
Dynamic: author
Dynamic: author-email
Dynamic: description
Dynamic: license
Dynamic: license-file
Dynamic: maintainer
Dynamic: maintainer-email
Dynamic: platform
Dynamic: summary
